Workbook

Sheet Assumptions
A1: PAYFLOW COMMERCE - Q4 2024 FINANCIAL MODEL
A2: =REPT("=",75) -> ===========================================================================
A4: KEY ASSUMPTIONS
A6: Revenue (Actuals - Q4 2024)
A8: October Revenue | B8: 1954516
A9: November Revenue | B9: 2379298
A10: December Revenue | B10: 2722787
A11: Q4 Total Revenue | B11: =B8+B9+B10 -> 7056601
A13: Cost Structure
A15: COGS % of Revenue | B15: 0.7
A16: Gross Margin % | B16: 0.3
A18: Operating Expenses (% of Revenue)
A20: Sales & Marketing | B20: 0.1
A21: Fraud Prevention | B21: 0.02
A22: Technology | B22: 0.05
A23: G&A | B23: 0.06
A24: Total OpEx % | B24: =B20+B21+B22+B23 -> 0.23
A26: Fraud Metrics
A28: Actual Fraud Rate (Q4 2024) | B28: 0.0183
A30: Q1 2025 Forecast
A32: Revenue Growth Rate | B32: 0.06
A33: Q1 2025 Revenue | B33: 7480000
A34: Target Fraud Rate (Q1) | B34: 0.015

Sheet Income Statement
A1: PAYFLOW COMMERCE | B1: October | C1: November | D1: December | E1: Q4 Total
A2: INCOME STATEMENT | B2: Q4 2024 | C2: Q4 2024 | D2: Q4 2024 | E2: Q4 2024
A3: All figures in USD | B3: $ | C3: $ | D3: $ | E3: $
A5: Revenue | B5: =Assumptions!B8 -> 1954516 | C5: =Assumptions!B9 -> 2379298 | D5: =Assumptions!B10 -> 2722787 | E5: =SUM(B5:D5) -> 7056601
A6: COGS | B6: =B5*Assumptions!$B$15 -> 1368161.2 | C6: =C5*Assumptions!$B$15 -> 1665508.6 | D6: =D5*Assumptions!$B$15 -> 1905950.9 | E6: =SUM(B6:D6) -> 4939620.7
A7: Gross Profit | B7: =B5-B6 -> 586354.8 | C7: =C5-C6 -> 713789.4 | D7: =D5-D6 -> 816836.1 | E7: =SUM(B7:D7) -> 2116980.3
A8: Gross Margin % | B8: =B7/B5 -> 0.3 | C8: =C7/C5 -> 0.3 | D8: =D7/D5 -> 0.3 | E8: =E7/E5 -> 0.3
A10: Operating Expenses:
A11: Sales & Marketing | B11: =B5*Assumptions!$B$20 -> 195451.6 | C11: =C5*Assumptions!$B$20 -> 237929.8 | D11: =D5*Assumptions!$B$20 -> 272278.7 | E11: =SUM(B11:D11) -> 705660.1
A12: Fraud Prevention | B12: =B5*Assumptions!$B$21 -> 39090.32 | C12: =C5*Assumptions!$B$21 -> 47585.96 | D12: =D5*Assumptions!$B$21 -> 54455.74 | E12: =SUM(B12:D12) -> 141132.02
A13: Technology | B13: =B5*Assumptions!$B$22 -> 97725.8 | C13: =C5*Assumptions!$B$22 -> 118964.9 | D13: =D5*Assumptions!$B$22 -> 136139.35 | E13: =SUM(B13:D13) -> 352830.05
A14: G&A | B14: =B5*Assumptions!$B$23 -> 117270.96 | C14: =C5*Assumptions!$B$23 -> 142757.88 | D14: =D5*Assumptions!$B$23 -> 163367.22 | E14: =SUM(B14:D14) -> 423396.06
A15: Total OpEx | B15: =SUM(B11:B14) -> 449538.68 | C15: =SUM(C11:C14) -> 547238.54 | D15: =SUM(D11:D14) -> 626241.01 | E15: =SUM(B15:D15) -> 1623018.2
A17: Operating Income | B17: =B7-B15 -> 136816.12 | C17: =C7-C15 -> 166550.86 | D17: =D7-D15 -> 190595.09 | E17: =SUM(B17:D17) -> 493962.07
A18: Operating Margin % | B18: =B17/B5 -> 0.07 | C18: =C17/C5 -> 0.07 | D18: =D17/D5 -> 0.07 | E18: =E17/E5 -> 0.07
A20: Fraud Losses | B20: =B5*Assumptions!$B$28 -> 35767.643 | C20: =C5*Assumptions!$B$28 -> 43541.153 | D20: =D5*Assumptions!$B$28 -> 49827.002 | E20: =SUM(B20:D20) -> 129135.8
A22: Net Income | B22: =B17-B20 -> 101048.48 | C22: =C17-C20 -> 123009.71 | D22: =D17-D20 -> 140768.09 | E22: =SUM(B22:D22) -> 364826.27
A23: Net Margin % | B23: =B22/B5 -> 0.0517 | C23: =C22/C5 -> 0.0517 | D23: =D22/D5 -> 0.0517 | E23: =E22/E5 -> 0.0517

Sheet Balance Sheet
A1: PAYFLOW COMMERCE - BALANCE SHEET (Q4 2024)
A2: All figures in USD
A4: ASSETS
A6: Cash | B6: ='Cash Flow'!B26 -> 1264826.3
A7: Accounts Receivable | B7: 450000
A8: Inventory | B8: 200000
A9: Total Current Assets | B9: =SUM(B6:B8) -> 1914826.3
A11: Fixed Assets | B11: 300000
A12: Total Assets | B12: =B9+B11 -> 2214826.3
A14: LIABILITIES
A16: Accounts Payable | B16: 350000
A17: Accrued Expenses | B17: 150000
A18: Total Liabilities | B18: =SUM(B16:B17) -> 500000
A20: EQUITY
A22: Common Stock | B22: 1000000
A23: Beginning Retained Earnings | B23: =B12-B18-B22-B24 -> 350000
A24: Net Income (Q4 2024) | B24: ='Income Statement'!E22 -> 364826.27
A25: Total Equity | B25: =SUM(B22:B24) -> 1714826.3
A26: Total Liabilities & Equity | B26: =B18+B25 -> 2214826.3

Sheet Cash Flow
A1: PAYFLOW COMMERCE - CASH FLOW STATEMENT (Q4 2024)
A2: All figures in USD
A4: Cash Flow from Operating Activities
A6: Net Income | B6: ='Income Statement'!E22 -> 364826.27
A8: Adjustments:
A9: Depreciation & Amortization | B9: 15000
A10: Accounts Receivable (increase) | B10: -50000
A11: Inventory (increase) | B11: -30000
A12: Accounts Payable increase | B12: 40000
A13: Accrued Expenses increase | B13: 25000
A14: Net Cash from Operations | B14: =SUM(B6:B13) -> 364826.27
A16: Cash Flow from Investing Activities
A17: Purchase of Fixed Assets | B17: -100000
A18: Net Cash from Investing | B18: =B17 -> -100000
A20: Cash Flow from Financing Activities
A21: No financing activity | B21: 0
A22: Net Cash from Financing | B22: =B21 -> 0
A24: Net Change in Cash | B24: =B14+B18+B22 -> 264826.27
A25: Beginning Cash | B25: 1000000
A26: Ending Cash | B26: =B24+B25 -> 1264826.3

Sheet Variance Analysis
A1: PAYFLOW COMMERCE | B1: Budget | C1: Actual | D1: Variance | E1: Variance %
A2: VARIANCE ANALYSIS | B2: Q4 2024 | C2: Q4 2024 | D2: $ | E2: %
A5: Revenue | B5: 6060000 | C5: ='Income Statement'!E5 -> 7056601 | D5: =C5-B5 -> 996601 | E5: =D5/B5 -> 0.16445561
A7: Gross Profit | B7: 1818000 | C7: ='Income Statement'!E7 -> 2116980.3 | D7: =C7-B7 -> 298980.3 | E7: =D7/B7 -> 0.16445561
A8: Gross Margin % | B8: 0.3 | C8: ='Income Statement'!E8 -> 0.3 | D8: =C8-B8 -> 0 | E8: =D8/B8 -> 0
A10: Operating Income | B10: 424200 | C10: ='Income Statement'!E17 -> 493962.07 | D10: =C10-B10 -> 69762.07 | E10: =D10/B10 -> 0.16445561
A11: Operating Margin % | B11: 0.07 | C11: ='Income Statement'!E18 -> 0.07 | D11: =C11-B11 -> 0 | E11: =D11/B11 -> 0
A13: Fraud Losses | B13: -121200 | C13: =-'Income Statement'!E20 -> -129135.8 | D13: =C13-B13 -> -7935.7983 | E13: =D13/B13 -> 0.065476884
A14: Fraud Rate % | B14: 0.02 | C14: =ABS(C13/C5) -> 0.0183 | D14: =C14-B14 -> -0.0017 | E14: =D14/B14 -> -0.085
A16: Net Income | B16: 303000 | C16: ='Income Statement'!E22 -> 364826.27 | D16: =C16-B16 -> 61826.272 | E16: =D16/B16 -> 0.2040471
A17: Net Margin % | B17: 0.05 | C17: ='Income Statement'!E23 -> 0.0517 | D17: =C17-B17 -> 0.0017 | E17: =D17/B17 -> 0.034
A19: KEY INSIGHTS:
A20: Revenue exceeded budget by 16.4% ($997K) due to strong December sales
A21: Gross profit increased proportionally (+16.4% or $299K)
A22: Operating income beat budget by 16.4% ($70K favorable variance)
A23: Fraud losses came in below budget - fraud prevention systems effective
A24: Net income $62K above budget (+20.4% favorable variance)

Sheet Q1 2025 Forecast
A1: PAYFLOW COMMERCE - Q1 2025 FORECAST
A2: =REPT("=",72) -> ========================================================================
A3: Forecast Assumptions
A4: KEY ASSUMPTIONS
A6: Q4 Revenue | B6: ='Income Statement'!E5 -> 7056601
A7: Sequential Growth | B7: =Assumptions!B32 -> 0.06
A8: Q1 Revenue Forecast | B8: =B6*(1+B7) -> 7479997.1
A10: Current Fraud Rate | B10: =Assumptions!B28 -> 0.0183
A11: New Fraud Rate (with controls) | B11: =Assumptions!B34 -> 0.015
A12: Expected Improvement | B12: =B10-B11 -> 0.0033
A14: Q1 2025 PROJECTED INCOME STATEMENT
A16: Revenue | B16: =B8 -> 7479997.1
A17: COGS (70%) | B17: =B16*0.7 -> 5235997.9
A18: Gross Profit | B18: =B16-B17 -> 2243999.1
A19: Gross Margin % | B19: =B18/B16 -> 0.3
A21: Operating Expenses (23%) | B21: =B16*0.23 -> 1720399.3
A22: Operating Income | B22: =B18-B21 -> 523599.79
A23: Operating Margin % | B23: =B22/B16 -> 0.07
A25: Fraud Losses (1.3%) | B25: =B16*B11 -> 112199.96
A26: Fraud Rate % | B26: =B25/B16 -> 0.015
A28: Net Income | B28: =B18-B21-B25 -> 411399.84
A29: Net Margin % | B29: =B28/B16 -> 0.055
A31: IMPROVEMENT VS Q4
A33: Q4 24 Net Income | B33: ='Income Statement'!E22 -> 364826.27
A34: Q1 25 Net Income | B34: =B28 -> 411399.84
A35: Improvement | B35: =B34-B33 -> 46573.567
A37: KEY TAKEAWAYS:
A38: Q1 revenue projected at $7.48M (6% sequential growth)
A39: Improved fraud controls expected to reduce fraud rate from 1.83% to 1.5%
A40: Net margin forecast to improve to 5.5% (up from 5.2% in Q4)
A41: Operating leverage driving margin expansion despite modest revenue growth
